[
  {
    "name": "Philippe Winter",
    "email": "email_not_unlocked@domain.com",
    "company": "Squadron Aviation Services Ltd.",
    "title": "Lead CaptainLead Captain"
  },
  {
    "name": "Mike Braham",
    "email": "email_not_unlocked@domain.com",
    "company": "Intempo Health",
    "title": "Chief Growth Officer and Board of Directors"
  },
  {
    "name": "Bill G",
    "email": "email_not_unlocked@domain.com",
    "company": "Breakthrough Energy",
    "title": "Founder"
  }
]